painy/__init__.py
painy/chat.py
painy/comment.py
painy/enums.py
painy/git.py
painy/main.py
painy/managers.py
painy/utils.py
painy/errors/GitDiffException.py
painy/errors/NoChangesException.py
painy/errors/NoSettingException.py
painy/errors/__init__.py
painy/settings/config.json
painy/settings/p_extensions.txt
painy/settings/prompt_comment_base.txt
painy/settings/prompt_commit_style.txt
painy/settings/rules.json
Painy-0.2.2.dist-info/LICENSE
Painy-0.2.2.dist-info/METADATA
Painy-0.2.2.dist-info/WHEEL
Painy-0.2.2.dist-info/entry_points.txt
Painy-0.2.2.dist-info/top_level.txt
Painy-0.2.2.dist-info/RECORD
