Metadata-Version: 2.1
Name: Painy
Version: 0.2.2
Summary: UNKNOWN
Home-page: https://github.com/lanesket/painy
Author: Raevskiy Rudolf
License: UNKNOWN
Platform: UNKNOWN
Classifier: Programming Language :: Python :: 3
Classifier: License :: OSI Approved :: MIT License
Classifier: Operating System :: OS Independent
Requires-Python: >=3.7.1
License-File: LICENSE
Requires-Dist: openai (==0.27.2)
Requires-Dist: tiktoken (==0.3.0)
Requires-Dist: nbdime (==3.1.1)
Requires-Dist: rich (==13.4.2)
Requires-Dist: langchain (==0.0.350)
Requires-Dist: langchain-core (==0.1.0)
